ScalaProcessUtils/__init__.py
pyrecdp/__init__.py
pyrecdp/ScalaProcessUtils/__init__.py
pyrecdp/ScalaProcessUtils/spark-defaults.conf
pyrecdp/ScalaProcessUtils/spark-env.sh
pyrecdp/ScalaProcessUtils/target/recdp-scala-extensions-0.1.0-jar-with-dependencies.jar
pyrecdp/autofe/AutoFE.py
pyrecdp/autofe/BasePipeline.py
pyrecdp/autofe/FeatureProfiler.py
pyrecdp/autofe/FeatureWrangler.py
pyrecdp/autofe/RelationalBuilder.py
pyrecdp/autofe/__init__.py
pyrecdp/core/__init__.py
pyrecdp/core/dataframe.py
pyrecdp/core/di_graph.py
pyrecdp/core/schema.py
pyrecdp/core/utils.py
pyrecdp/datasets/__init__.py
pyrecdp/datasets/amazon_product_review.py
pyrecdp/datasets/base_api.py
pyrecdp/datasets/nyc_taxi.py
pyrecdp/datasets/outbrain.py
pyrecdp/datasets/twitter_recsys.py
pyrecdp/primitives/__init__.py
pyrecdp/primitives/generators/__init__.py
pyrecdp/primitives/generators/base.py
pyrecdp/primitives/generators/binned.py
pyrecdp/primitives/generators/category.py
pyrecdp/primitives/generators/dataframe.py
pyrecdp/primitives/generators/datetime.py
pyrecdp/primitives/generators/drop.py
pyrecdp/primitives/generators/encoder.py
pyrecdp/primitives/generators/featuretools_adaptor.py
pyrecdp/primitives/generators/fillna.py
pyrecdp/primitives/generators/geograph.py
pyrecdp/primitives/generators/name.py
pyrecdp/primitives/generators/nlp.py
pyrecdp/primitives/generators/relation.py
pyrecdp/primitives/generators/statics.py
pyrecdp/primitives/generators/type.py
pyrecdp/primitives/operations/__init__.py
pyrecdp/primitives/operations/base.py
pyrecdp/primitives/operations/category.py
pyrecdp/primitives/operations/data.py
pyrecdp/primitives/operations/dataframe.py
pyrecdp/primitives/operations/datetime.py
pyrecdp/primitives/operations/drop.py
pyrecdp/primitives/operations/featuretools_adaptor.py
pyrecdp/primitives/operations/fillna.py
pyrecdp/primitives/operations/geograph.py
pyrecdp/primitives/operations/merge.py
pyrecdp/primitives/operations/name.py
pyrecdp/primitives/operations/nlp.py
pyrecdp-1.0.1b20230307.dist-info/LICENSE
pyrecdp-1.0.1b20230307.dist-info/METADATA
pyrecdp-1.0.1b20230307.dist-info/WHEEL
pyrecdp-1.0.1b20230307.dist-info/top_level.txt
pyrecdp-1.0.1b20230307.dist-info/RECORD
