Metadata-Version: 2.1
Name: pyrecdp
Version: 1.0.1b20230307
Summary: A data processing bundle for spark based recommender system operations
Home-page: https://github.com/intel/e2eAIOK/
Author: INTEL AIA
Author-email: chendi.xue@intel.com
License: UNKNOWN
Project-URL: Bug Tracker, https://github.com/intel/e2eAIOK/
Platform: UNKNOWN
Classifier: Programming Language :: Python :: 3
Classifier: License :: OSI Approved :: Apache Software License
Classifier: Operating System :: OS Independent
Requires-Python: >=3.6
License-File: LICENSE
Requires-Dist: bokeh (>=2.4.2)
Requires-Dist: boto3
Requires-Dist: distro
Requires-Dist: featuretools
Requires-Dist: graphviz
Requires-Dist: ipywidgets
Requires-Dist: jupyter
Requires-Dist: lightgbm
Requires-Dist: numpy
Requires-Dist: pandas
Requires-Dist: pandas-flavor
Requires-Dist: plotly
Requires-Dist: psutil
Requires-Dist: pyarrow
Requires-Dist: pyspark (==3.3.1)
Requires-Dist: pyyaml
Requires-Dist: requests
Requires-Dist: scikit-learn
Requires-Dist: shapely
Requires-Dist: tqdm
Requires-Dist: transformers
